waveletml/__init__.py
waveletml/helpers/__init__.py
waveletml/helpers/callbacks.py
waveletml/helpers/data_preparer.py
waveletml/helpers/data_scaler.py
waveletml/helpers/evaluator.py
waveletml/helpers/verifier.py
waveletml/helpers/wavelet_funcs.py
waveletml/helpers/wavelet_layers.py
waveletml/models/__init__.py
waveletml/models/base_model.py
waveletml/models/custom_wnn.py
waveletml/models/gd_wnn.py
waveletml/models/mha_wnn.py
waveletml-0.2.0.dist-info/licenses/LICENSE
waveletml-0.2.0.dist-info/METADATA
waveletml-0.2.0.dist-info/WHEEL
waveletml-0.2.0.dist-info/top_level.txt
waveletml-0.2.0.dist-info/RECORD
